django_tinywiki/__init__.py
django_tinywiki/admin.py
django_tinywiki/apps.py
django_tinywiki/decorators.py
django_tinywiki/settings.py
django_tinywiki/tests.py
django_tinywiki/urls.py
django_tinywiki/version.py
django_tinywiki/builtin_wiki_pages/Lama.jpg
django_tinywiki/builtin_wiki_pages/__init__.py
django_tinywiki/builtin_wiki_pages/de.index.md
django_tinywiki/builtin_wiki_pages/de.markdown.md
django_tinywiki/builtin_wiki_pages/de.settings.md
django_tinywiki/builtin_wiki_pages/en.index.md
django_tinywiki/builtin_wiki_pages/en.license.md
django_tinywiki/builtin_wiki_pages/en.markdown.md
django_tinywiki/builtin_wiki_pages/en.settings.md
django_tinywiki/builtin_wiki_pages/vineyard-styria.jpg
django_tinywiki/forms/__init__.py
django_tinywiki/forms/auth.py
django_tinywiki/forms/wiki.py
django_tinywiki/functions/__init__.py
django_tinywiki/functions/auth.py
django_tinywiki/functions/init.py
django_tinywiki/functions/sidebar.py
django_tinywiki/functions/utils.py
django_tinywiki/functions/wiki.py
django_tinywiki/locale/de/LC_MESSAGES/django.mo
django_tinywiki/locale/de/LC_MESSAGES/django.po
django_tinywiki/markdown_extensions/__init__.py
django_tinywiki/markdown_extensions/copyright.py
django_tinywiki/markdown_extensions/delpattern.py
django_tinywiki/markdown_extensions/djangourl.py
django_tinywiki/markdown_extensions/tinywikiimage.py
django_tinywiki/markdown_extensions/tinywikilink.py
django_tinywiki/markdown_extensions/video.py
django_tinywiki/migrations/0001_initial.py
django_tinywiki/migrations/0002_alter_wikiimage_image_alter_wikiimage_image_preview_and_more.py
django_tinywiki/migrations/__init__.py
django_tinywiki/models/__init__.py
django_tinywiki/models/language.py
django_tinywiki/models/wiki.py
django_tinywiki/scripts/__init__.py
django_tinywiki/scripts/initapp.py
django_tinywiki/scripts/tinywiki_codehilite_styles.py
django_tinywiki/scripts/tinywiki_languages.py
django_tinywiki/scripts/tinywiki_styles.py
django_tinywiki/static/django_tinywiki/images/peacock.jpg
django_tinywiki-0.0.10.dist-info/LICENSE
django_tinywiki-0.0.10.dist-info/METADATA
django_tinywiki-0.0.10.dist-info/WHEEL
django_tinywiki-0.0.10.dist-info/top_level.txt
django_tinywiki-0.0.10.dist-info/RECORD
